{
    "buyer": {
        "address": "06899 Gross Mission Amybury, MS 77527",
        "email": "xhall@example.net",
        "phone": "001-723-721-7594x2836",
        "vat_no": "Ig41992453372"
    },
    "invoice": {
        "date": "13.08.2009",
        "due_date": "11.02.1991",
        "market_reference": 721685,
        "notes": "exploit out-of-the-box synergies",
        "number": "3597-6612",
        "reference": 411137,
        "vat_no": "fy80306874466"
    },
    "payment": {
        "net_total": 51.5,
        "total": 964.17
    },
    "products": [
        {
            "amount": 278.18,
            "description": "orchestrate enterprise methodologies",
            "hours": 3.57,
            "rate": 1.75
        },
        {
            "amount": 401.0,
            "description": "unleash plug-and-play synergies",
            "hours": 9.3,
            "rate": 7.64
        },
        {
            "amount": 28.97,
            "description": "facilitate integrated methodologies",
            "hours": 6.96,
            "rate": 4.99
        }
    ],
    "seller": {
        "address": "704 Stout Mission Apt. 067 Robinsonmouth, IL 35039",
        "email": "roseberry@example.net",
        "name": "Amanda Gibbs"
    },
    "tax": {
        "base": 14.91,
        "tax_amount": 13.84,
        "total_tax": 24.72
    }
}