{
    "buyer": {
        "address": "USCGC Stephens FPO AA 99890",
        "email": "omiles@example.com",
        "phone": "001-964-238-2794x60595",
        "vat_no": "oi12624754360"
    },
    "invoice": {
        "date": "10.08.2014",
        "due_date": "07.01.1996",
        "market_reference": 960042,
        "notes": "orchestrate proactive deliverables",
        "number": "0185-2738",
        "reference": 281567,
        "vat_no": "UP83083928849"
    },
    "payment": {
        "net_total": 160.51,
        "total": 191.93
    },
    "products": [
        {
            "amount": 426.88,
            "description": "seize revolutionary eyeballs",
            "hours": 7.12,
            "rate": 2.65
        },
        {
            "amount": 324.95,
            "description": "target scalable partnerships",
            "hours": 8.05,
            "rate": 2.76
        },
        {
            "amount": 92.22,
            "description": "facilitate frictionless channels",
            "hours": 8.56,
            "rate": 8.67
        },
        {
            "amount": 406.98,
            "description": "maximize 24/7 e-services",
            "hours": 3.17,
            "rate": 6.8
        }
    ],
    "seller": {
        "address": "45706 Todd Meadows Sabrinaport, MN 40417",
        "email": "shaneerickson@example.org",
        "name": "Justin Hensley"
    },
    "tax": {
        "base": 13.72,
        "tax_amount": 21.9,
        "total_tax": 20.63
    }
}