{
    "buyer": {
        "address": "6114 Jennifer Island West Carolchester, AR 08544",
        "email": "richdaniel@example.net",
        "phone": "5884475471",
        "vat_no": "yn45497717607"
    },
    "invoice": {
        "date": "10.06.2009",
        "due_date": "20.06.2007",
        "market_reference": 496709,
        "notes": "deploy value-added e-tailers",
        "number": "9871-8158",
        "reference": 733842,
        "vat_no": "vW88784412201"
    },
    "payment": {
        "net_total": 90.77,
        "total": 339.61
    },
    "products": [
        {
            "amount": 296.24,
            "description": "innovate revolutionary e-tailers",
            "hours": 2.89,
            "rate": 6.77
        },
        {
            "amount": 270.71,
            "description": "morph enterprise e-tailers",
            "hours": 1.41,
            "rate": 6.24
        },
        {
            "amount": 476.97,
            "description": "incubate viral methodologies",
            "hours": 6.84,
            "rate": 4.14
        },
        {
            "amount": 447.68,
            "description": "transition integrated channels",
            "hours": 8.68,
            "rate": 6.8
        },
        {
            "amount": 497.01,
            "description": "synthesize robust networks",
            "hours": 5.78,
            "rate": 5.88
        },
        {
            "amount": 295.36,
            "description": "aggregate rich models",
            "hours": 2.35,
            "rate": 3.72
        }
    ],
    "seller": {
        "address": "100 Michael Station North Jennifer, PW 67468",
        "email": "xgibson@example.com",
        "name": "Paul Reyes"
    },
    "tax": {
        "base": 15.61,
        "tax_amount": 11.04,
        "total_tax": 28.31
    }
}