{
    "buyer": {
        "address": "72052 Lewis Island Apt. 031 Robinsonville, MO 34909",
        "email": "stevenburns@example.org",
        "phone": "+1-545-961-4992x621",
        "vat_no": "Iy35931397177"
    },
    "invoice": {
        "date": "06.07.2011",
        "due_date": "01.08.1993",
        "market_reference": 772414,
        "notes": "evolve proactive eyeballs",
        "number": "2891-1887",
        "reference": 396007,
        "vat_no": "OZ85200161648"
    },
    "payment": {
        "net_total": 109.65,
        "total": 906.69
    },
    "products": [
        {
            "amount": 17.04,
            "description": "mesh killer users",
            "hours": 7.26,
            "rate": 6.87
        },
        {
            "amount": 376.04,
            "description": "optimize compelling web services",
            "hours": 4.81,
            "rate": 8.72
        },
        {
            "amount": 58.69,
            "description": "aggregate frictionless mindshare",
            "hours": 5.68,
            "rate": 2.34
        },
        {
            "amount": 29.88,
            "description": "deliver strategic interfaces",
            "hours": 3.78,
            "rate": 6.3
        },
        {
            "amount": 454.64,
            "description": "utilize plug-and-play markets",
            "hours": 1.83,
            "rate": 7.79
        },
        {
            "amount": 5.49,
            "description": "syndicate wireless initiatives",
            "hours": 2.93,
            "rate": 5.39
        }
    ],
    "seller": {
        "address": "Unit 0569 Box 4819 DPO AA 07634",
        "email": "umiller@example.org",
        "name": "Angela Bell"
    },
    "tax": {
        "base": 20.84,
        "tax_amount": 24.22,
        "total_tax": 18.49
    }
}