{
    "buyer": {
        "address": "89648 Collins Forest New Nicoleton, DC 12166",
        "email": "katherineholt@example.com",
        "phone": "(229)976-9636",
        "vat_no": "cG35805230357"
    },
    "invoice": {
        "date": "02.09.1991",
        "due_date": "12.01.1999",
        "market_reference": 887223,
        "notes": "visualize web-enabled models",
        "number": "0195-3469",
        "reference": 314089,
        "vat_no": "kj20293590185"
    },
    "payment": {
        "net_total": 58.71,
        "total": 483.59
    },
    "products": [
        {
            "amount": 186.49,
            "description": "maximize integrated users",
            "hours": 1.03,
            "rate": 9.57
        },
        {
            "amount": 34.94,
            "description": "expedite frictionless info-mediaries",
            "hours": 8.53,
            "rate": 9.04
        },
        {
            "amount": 495.13,
            "description": "synthesize sticky technologies",
            "hours": 5.83,
            "rate": 2.56
        }
    ],
    "seller": {
        "address": "103 Keith Alley East Michellemouth, VT 54213",
        "email": "stevenjordan@example.com",
        "name": "Megan Dillon"
    },
    "tax": {
        "base": 17.15,
        "tax_amount": 20.42,
        "total_tax": 12.16
    }
}