{
    "buyer": {
        "address": "946 Daniels Springs Suite 699 Morrowfort, ME 45005",
        "email": "lawsonlarry@example.org",
        "phone": "551.630.4799x44469",
        "vat_no": "hE67566413024"
    },
    "invoice": {
        "date": "10.09.2018",
        "due_date": "23.04.2005",
        "market_reference": 279507,
        "notes": "mesh user-centric web services",
        "number": "3537-8670",
        "reference": 660783,
        "vat_no": "VH55288516412"
    },
    "payment": {
        "net_total": 26.03,
        "total": 990.98
    },
    "products": [
        {
            "amount": 235.15,
            "description": "transform one-to-one e-tailers",
            "hours": 1.26,
            "rate": 2.79
        },
        {
            "amount": 175.75,
            "description": "re-intermediate customized e-business",
            "hours": 3.7,
            "rate": 6.34
        },
        {
            "amount": 87.37,
            "description": "monetize visionary e-tailers",
            "hours": 7.96,
            "rate": 8.12
        },
        {
            "amount": 472.64,
            "description": "cultivate distributed schemas",
            "hours": 8.17,
            "rate": 1.04
        },
        {
            "amount": 50.19,
            "description": "seize best-of-breed technologies",
            "hours": 3.16,
            "rate": 1.98
        }
    ],
    "seller": {
        "address": "377 Brandon Forges Suite 307 South Craig, NM 41444",
        "email": "cblair@example.net",
        "name": "Natasha Meza"
    },
    "tax": {
        "base": 29.54,
        "tax_amount": 24.7,
        "total_tax": 29.69
    }
}