{
    "buyer": {
        "address": "72418 Hatfield Key Apt. 787 Lake Richardfurt, IL 95236",
        "company_name": "Harris, Jones and Moore",
        "email": "rickey37@example.org",
        "name": "Carol Perez",
        "phone": "+1-497-780-4924x133"
    },
    "invoice": {
        "date": "13.11.2022",
        "due_date": "14.08.1995",
        "number": "IZg32732647521"
    },
    "payment": {
        "account_number": 5206099972,
        "bank_name": "Duke, Gonzalez and Stewart",
        "routing_number": 744167470
    },
    "products": [
        {
            "amount": 474.62,
            "description": "harness real-time content",
            "index": "6",
            "quantity": 6.33,
            "unit_price": 17.84
        },
        {
            "amount": 388.66,
            "description": "transition proactive networks",
            "index": "1",
            "quantity": 2.04,
            "unit_price": 88.72
        },
        {
            "amount": 54.24,
            "description": "e-enable bricks-and-clicks initiatives",
            "index": "7",
            "quantity": 2.49,
            "unit_price": 70.57
        },
        {
            "amount": 245.04,
            "description": "engineer plug-and-play info-mediaries",
            "index": "5",
            "quantity": 1.15,
            "unit_price": 19.52
        },
        {
            "amount": 111.57,
            "description": "integrate e-business e-markets",
            "index": "2",
            "quantity": 3.92,
            "unit_price": 61.33
        },
        {
            "amount": 433.23,
            "description": "incubate wireless ROI",
            "index": "7",
            "quantity": 9.63,
            "unit_price": 82.5
        },
        {
            "amount": 329.04,
            "description": "enable holistic supply-chains",
            "index": "9",
            "quantity": 1.9,
            "unit_price": 69.03
        }
    ],
    "seller": {
        "address": "93632 Samuel Vista Marshberg, OK 69031",
        "company_name": "Walters, Rodriguez and Santiago",
        "email": "nclark@example.com"
    }
}