{
    "buyer": {
        "address": "1210 Sullivan Motorway Suite 639 Mandymouth, PA 65688",
        "company_name": "Morris-Smith",
        "email": "jdiaz@example.org",
        "name": "Melissa Moore",
        "phone": "(863)854-0179x65746"
    },
    "invoice": {
        "date": "16.04.1992",
        "due_date": "07.09.1997",
        "number": "nsK69653054199"
    },
    "payment": {
        "account_number": 5908685208,
        "bank_name": "Sparks-Williams",
        "routing_number": 734869663
    },
    "products": [
        {
            "amount": 302.67,
            "description": "repurpose robust initiatives",
            "index": "2",
            "quantity": 5.89,
            "unit_price": 60.39
        },
        {
            "amount": 332.59,
            "description": "orchestrate integrated markets",
            "index": "9",
            "quantity": 8.82,
            "unit_price": 43.11
        },
        {
            "amount": 496.2,
            "description": "revolutionize value-added eyeballs",
            "index": "3",
            "quantity": 4.05,
            "unit_price": 85.83
        },
        {
            "amount": 452.43,
            "description": "drive synergistic convergence",
            "index": "3",
            "quantity": 1.81,
            "unit_price": 74.63
        },
        {
            "amount": 186.71,
            "description": "morph robust vortals",
            "index": "8",
            "quantity": 7.47,
            "unit_price": 31.66
        },
        {
            "amount": 138.52,
            "description": "iterate 24/365 convergence",
            "index": "7",
            "quantity": 6.33,
            "unit_price": 69.92
        },
        {
            "amount": 36.93,
            "description": "transform web-enabled mindshare",
            "index": "3",
            "quantity": 7.14,
            "unit_price": 38.51
        }
    ],
    "seller": {
        "address": "9168 Jeffery Ports Suite 706 Guerrerobury, NE 02778",
        "company_name": "Morris-Taylor",
        "email": "mcintoshmelinda@example.com"
    }
}