{
    "buyer": {
        "address": "865 Joseph Lock West Andrewview, SC 77885",
        "company_name": "Mosley, Moore and Garcia",
        "email": "juliawong@example.net",
        "name": "Melissa Bell",
        "phone": "381.697.7538x072"
    },
    "invoice": {
        "date": "31.07.2005",
        "due_date": "10.09.1992",
        "number": "WSc68122081983"
    },
    "payment": {
        "account_number": 1701423944,
        "bank_name": "Robertson-Johnson",
        "routing_number": 605349194
    },
    "products": [
        {
            "amount": 321.82,
            "description": "strategize B2B e-services",
            "index": "8",
            "quantity": 1.04,
            "unit_price": 53.2
        }
    ],
    "seller": {
        "address": "91077 Baker Plaza Suite 709 Robinsonport, MD 23527",
        "company_name": "Delacruz-Doyle",
        "email": "laura37@example.net"
    }
}