{
    "buyer": {
        "address": "24538 James Mount North Anthonyfort, TX 78188",
        "company_name": "Frey, Lara and Wilson",
        "country": "Reunion",
        "email": "thompsondylan@example.com",
        "name": "Eugene Parker",
        "phone": "(408)287-9845",
        "vat_no": "ra25251965234"
    },
    "invoice": {
        "date": "10.04.2006",
        "due_date": "12.04.2023",
        "linked_invoice": "mW-5551-8319",
        "notes": "implement vertical vortals",
        "number": "rL-9942-1700"
    },
    "products": [
        {
            "description": "implement integrated portals",
            "discount_percentage": 5.8,
            "price": 481.52,
            "quantity": 7.6,
            "unit_price": 71.85
        },
        {
            "description": "iterate robust convergence",
            "discount_percentage": 9.1,
            "price": 369.32,
            "quantity": 8.68,
            "unit_price": 44.08
        },
        {
            "description": "transition real-time synergies",
            "discount_percentage": 15.57,
            "price": 170.85,
            "quantity": 9.73,
            "unit_price": 22.27
        }
    ],
    "seller": {
        "address": "303 Angela Mountains Suite 945 New Meghan, NC 30651",
        "ape": "4555U",
        "capital": 53337026,
        "country": "Antarctica (the territory South of 60 deg S)",
        "email": "amandalee@example.com",
        "name": "Rachael Watson",
        "phone_1": "384.359.6579",
        "phone_2": "(339)991-4888",
        "phone_3": "(747)243-4245x7540",
        "ref_walk": "CJwq2655",
        "reference": "MB799",
        "siret": 32965465246208,
        "vat_no": "kP93333687611",
        "website": "http://thompson-harper.com/"
    },
    "tax": {
        "amount_0": 15.49,
        "amount_1": 27.97,
        "base_0": 10.81,
        "base_1": 61.01,
        "total_ht": 350.47,
        "total_tax": 20.77,
        "total_ttc": 442.57,
        "vat_0": 17.55,
        "vat_1": 10.45
    }
}