{
    "buyer": {
        "address": "7740 Shawn Mountain Suite 941 Lake Allison, MD 43425",
        "company_name": "Lawson Inc",
        "country": "Martinique",
        "email": "jesus56@example.com",
        "name": "Wesley Edwards",
        "phone": "946-894-8746x116",
        "vat_no": "tB53781031140"
    },
    "invoice": {
        "date": "07.04.2006",
        "due_date": "03.05.1994",
        "linked_invoice": "Af-6231-8102",
        "notes": "synthesize collaborative synergies",
        "number": "bx-7842-5912"
    },
    "products": [
        {
            "description": "integrate visionary deliverables",
            "discount_percentage": 5.33,
            "price": 317.76,
            "quantity": 5.69,
            "unit_price": 35.49
        },
        {
            "description": "grow holistic mindshare",
            "discount_percentage": 5.6,
            "price": 184.26,
            "quantity": 8.95,
            "unit_price": 37.78
        },
        {
            "description": "maximize out-of-the-box web-readiness",
            "discount_percentage": 16.92,
            "price": 242.11,
            "quantity": 3.25,
            "unit_price": 60.77
        },
        {
            "description": "implement dot-com platforms",
            "discount_percentage": 9.56,
            "price": 319.43,
            "quantity": 7.97,
            "unit_price": 13.96
        },
        {
            "description": "engineer cross-media applications",
            "discount_percentage": 19.96,
            "price": 159.18,
            "quantity": 3.3,
            "unit_price": 39.3
        },
        {
            "description": "envisioneer ubiquitous models",
            "discount_percentage": 19.26,
            "price": 100.0,
            "quantity": 3.61,
            "unit_price": 92.08
        }
    ],
    "seller": {
        "address": "USS Williams FPO AE 60257",
        "ape": "9982i",
        "capital": 98047485,
        "country": "Uganda",
        "email": "wigginsmonica@example.com",
        "name": "Timothy Collins",
        "phone_1": "681.608.6625x7801",
        "phone_2": "001-216-302-4781",
        "phone_3": "214-770-3933x88939",
        "ref_walk": "Ojyo1607",
        "reference": "Me053",
        "siret": 49184570325658,
        "vat_no": "Oy71683870117",
        "website": "http://gallagher.com/"
    },
    "tax": {
        "amount_0": 18.15,
        "amount_1": 20.51,
        "base_0": 15.61,
        "base_1": 74.57,
        "total_ht": 422.74,
        "total_tax": 16.09,
        "total_ttc": 406.89,
        "vat_0": 29.67,
        "vat_1": 15.73
    }
}