{
    "buyer": {
        "address": "0186 Johnson Estates Apt. 515 North Kelly, IL 03015",
        "company_name": "Alexander, Adams and Maynard",
        "country": "Netherlands Antilles",
        "email": "ghudson@example.org",
        "name": "James Alvarez Jr.",
        "phone": "221.218.9463x1618",
        "vat_no": "vz47877538045"
    },
    "invoice": {
        "date": "11.06.2002",
        "due_date": "29.07.2020",
        "linked_invoice": "Jk-0766-4762",
        "notes": "drive transparent functionalities",
        "number": "XZ-0045-8547"
    },
    "products": [
        {
            "description": "architect mission-critical partnerships",
            "discount_percentage": 13.43,
            "price": 358.08,
            "quantity": 9.89,
            "unit_price": 95.0
        },
        {
            "description": "monetize frictionless niches",
            "discount_percentage": 19.47,
            "price": 328.07,
            "quantity": 6.66,
            "unit_price": 24.46
        },
        {
            "description": "implement bleeding-edge e-commerce",
            "discount_percentage": 19.65,
            "price": 279.04,
            "quantity": 9.42,
            "unit_price": 88.22
        }
    ],
    "seller": {
        "address": "4762 Joshua Park Apt. 825 Lancehaven, DC 39707",
        "ape": "9437P",
        "capital": 35000576,
        "country": "Turkmenistan",
        "email": "robertgriffith@example.com",
        "name": "David Galloway",
        "phone_1": "001-384-519-7681x843",
        "phone_2": "(433)459-0168",
        "phone_3": "(553)492-7945",
        "ref_walk": "zapS3070",
        "reference": "gI838",
        "siret": 17797440553519,
        "vat_no": "tm59761947119",
        "website": "https://lee.com/"
    },
    "tax": {
        "amount_0": 15.56,
        "amount_1": 25.1,
        "base_0": 11.59,
        "base_1": 228.4,
        "total_ht": 433.41,
        "total_tax": 21.33,
        "total_ttc": 458.01,
        "vat_0": 20.46,
        "vat_1": 12.05
    }
}