{
    "buyer": {
        "address": "5184 Megan Bypass Suite 676 Gibsonburgh, DE 42347",
        "company_name": "Simpson Inc",
        "country": "Palau",
        "email": "kennethcasey@example.org",
        "name": "Lauren Mendez",
        "phone": "(696)552-3857x855",
        "vat_no": "kN57261075791"
    },
    "invoice": {
        "date": "03.06.2009",
        "due_date": "10.11.2014",
        "linked_invoice": "WT-0441-7074",
        "notes": "streamline cutting-edge partnerships",
        "number": "Ie-6168-5939"
    },
    "products": [
        {
            "description": "orchestrate cutting-edge architectures",
            "discount_percentage": 5.71,
            "price": 52.42,
            "quantity": 4.84,
            "unit_price": 16.2
        },
        {
            "description": "productize intuitive paradigms",
            "discount_percentage": 6.21,
            "price": 472.22,
            "quantity": 6.15,
            "unit_price": 95.73
        },
        {
            "description": "repurpose rich applications",
            "discount_percentage": 13.51,
            "price": 265.19,
            "quantity": 7.98,
            "unit_price": 78.02
        },
        {
            "description": "grow customized partnerships",
            "discount_percentage": 13.89,
            "price": 496.87,
            "quantity": 8.04,
            "unit_price": 61.2
        },
        {
            "description": "orchestrate end-to-end functionalities",
            "discount_percentage": 16.32,
            "price": 131.36,
            "quantity": 1.89,
            "unit_price": 81.67
        },
        {
            "description": "brand next-generation methodologies",
            "discount_percentage": 17.89,
            "price": 382.87,
            "quantity": 8.2,
            "unit_price": 34.86
        },
        {
            "description": "unleash compelling e-markets",
            "discount_percentage": 12.23,
            "price": 433.33,
            "quantity": 9.15,
            "unit_price": 77.76
        }
    ],
    "seller": {
        "address": "729 Margaret Turnpike Suite 945 Lake Roy, NV 16076",
        "ape": "5786s",
        "capital": 88541410,
        "country": "Georgia",
        "email": "ramirezdanielle@example.net",
        "name": "Kathleen Trujillo",
        "phone_1": "(644)851-8781",
        "phone_2": "815-856-2416x49137",
        "phone_3": "933.325.3792",
        "ref_walk": "PtvF5234",
        "reference": "jY859",
        "siret": 58129267269427,
        "vat_no": "Zs73508685429",
        "website": "https://www.bradley.org/"
    },
    "tax": {
        "amount_0": 10.75,
        "amount_1": 28.89,
        "base_0": 17.4,
        "base_1": 228.76,
        "total_ht": 275.37,
        "total_tax": 17.45,
        "total_ttc": 301.48,
        "vat_0": 17.82,
        "vat_1": 14.99
    }
}