{
    "buyer": {
        "address": "8739 Laura Summit West Thomaschester, MN 56631",
        "company_name": "Baker-Brooks",
        "country": "Senegal",
        "name": "Brian Robinson"
    },
    "invoice": {
        "date": "09.11.2001",
        "number": 321803
    },
    "payment": {
        "discount_amount": 48.55,
        "discount_percentage": 15.8,
        "due": 59.96,
        "sub_total": 166.46,
        "total": 908.36
    },
    "products": [
        {
            "description": "optimize customized networks",
            "index": "3",
            "quantity": 3.15,
            "total_price": 389.67,
            "unit_price": 37.7
        },
        {
            "description": "optimize intuitive metrics",
            "index": "10",
            "quantity": 3.39,
            "total_price": 944.4,
            "unit_price": 17.8
        },
        {
            "description": "scale 24/7 vortals",
            "index": "4",
            "quantity": 3.44,
            "total_price": 491.08,
            "unit_price": 79.42
        },
        {
            "description": "deploy open-source initiatives",
            "index": "7",
            "quantity": 2.34,
            "total_price": 148.66,
            "unit_price": 96.28
        },
        {
            "description": "exploit plug-and-play interfaces",
            "index": "5",
            "quantity": 7.72,
            "total_price": 558.31,
            "unit_price": 96.05
        },
        {
            "description": "optimize visionary applications",
            "index": "9",
            "quantity": 5.55,
            "total_price": 918.08,
            "unit_price": 37.62
        }
    ],
    "seller": {
        "address": "16627 Williams Ways Suite 333 Blackburnbury, PW 42401",
        "company_name": "Kent-Kennedy",
        "vat_no": "fK92008298440"
    }
}