{
    "buyer": {
        "address": "116 Sampson Stravenue Whitehaven, NC 59718"
    },
    "invoice": {
        "bc_no": "zJ23872",
        "date": "07.06.1992",
        "maturity_date": "19.09.1998",
        "number": 808224
    },
    "products": [
        {
            "amount": 241.04,
            "description": "maximize innovative synergies",
            "quantity": 6.26,
            "unit_price": 39.33,
            "vat_amount": 1.91
        },
        {
            "amount": 215.01,
            "description": "optimize 24/7 channels",
            "quantity": 9.07,
            "unit_price": 33.28,
            "vat_amount": 0.18
        },
        {
            "amount": 80.93,
            "description": "exploit scalable info-mediaries",
            "quantity": 3.6,
            "unit_price": 44.48,
            "vat_amount": 9.36
        },
        {
            "amount": 286.15,
            "description": "generate dynamic content",
            "quantity": 1.85,
            "unit_price": 82.93,
            "vat_amount": 10.26
        },
        {
            "amount": 335.15,
            "description": "innovate rich web services",
            "quantity": 7.74,
            "unit_price": 92.63,
            "vat_amount": 2.56
        },
        {
            "amount": 128.96,
            "description": "maximize synergistic systems",
            "quantity": 3.29,
            "unit_price": 90.15,
            "vat_amount": 7.78
        },
        {
            "amount": 74.07,
            "description": "iterate wireless supply-chains",
            "quantity": 1.14,
            "unit_price": 87.54,
            "vat_amount": 11.94
        }
    ],
    "seller": {
        "address": "050 Riddle Place Apt. 895 Krystalmouth, NH 60331"
    },
    "tax": {
        "amount_excluding_tax": 130.1,
        "amount_including_tax": 183.87,
        "tax_amount": 12.36
    }
}