{
    "buyer": {
        "address": "PSC 1564, Box 9594 APO AA 71353"
    },
    "invoice": {
        "bc_no": "My96432",
        "date": "23.12.2019",
        "maturity_date": "19.02.2017",
        "number": 342632
    },
    "products": [
        {
            "amount": 261.76,
            "description": "re-intermediate revolutionary web-readiness",
            "quantity": 6.25,
            "unit_price": 41.09,
            "vat_amount": 1.41
        },
        {
            "amount": 292.52,
            "description": "extend cross-media models",
            "quantity": 5.25,
            "unit_price": 50.85,
            "vat_amount": 17.36
        },
        {
            "amount": 79.99,
            "description": "envisioneer impactful paradigms",
            "quantity": 6.7,
            "unit_price": 89.78,
            "vat_amount": 0.83
        },
        {
            "amount": 5.84,
            "description": "brand sticky models",
            "quantity": 4.62,
            "unit_price": 43.28,
            "vat_amount": 1.2
        },
        {
            "amount": 306.16,
            "description": "redefine wireless platforms",
            "quantity": 1.4,
            "unit_price": 58.52,
            "vat_amount": 0.0
        }
    ],
    "seller": {
        "address": "755 Laurie Drive North Katieport, NE 43196"
    },
    "tax": {
        "amount_excluding_tax": 65.0,
        "amount_including_tax": 193.83,
        "tax_amount": 13.29
    }
}