{
    "buyer": {
        "address": "39501 Robinson Fort Suite 468 Peggyland, UT 96764",
        "business_no": "pK231",
        "id": "Zp555"
    },
    "invoice": {
        "date": "15.10.2020",
        "number": "0282-6661"
    },
    "payment": {
        "due_date": "24.06.2021",
        "total": 563.76
    },
    "products": [
        {
            "amount": 66.27,
            "description": "leverage ubiquitous e-tailers",
            "quantity": 9.72,
            "reference": "fa-879",
            "unit_price": 30.35
        },
        {
            "amount": 52.6,
            "description": "visualize clicks-and-mortar e-services",
            "quantity": 1.1,
            "reference": "Qv-036",
            "unit_price": 29.55
        },
        {
            "amount": 403.69,
            "description": "empower collaborative vortals",
            "quantity": 5.89,
            "reference": "Ln-138",
            "unit_price": 38.43
        },
        {
            "amount": 85.91,
            "description": "evolve interactive channels",
            "quantity": 5.03,
            "reference": "Ut-401",
            "unit_price": 80.76
        },
        {
            "amount": 23.93,
            "description": "utilize value-added content",
            "quantity": 7.61,
            "reference": "oN-321",
            "unit_price": 83.9
        },
        {
            "amount": 176.67,
            "description": "incubate front-end synergies",
            "quantity": 8.23,
            "reference": "hp-547",
            "unit_price": 28.37
        },
        {
            "amount": 493.58,
            "description": "innovate next-generation interfaces",
            "quantity": 6.73,
            "reference": "xX-534",
            "unit_price": 60.88
        }
    ],
    "seller": {
        "address": "Unit 0636 Box 8146 DPO AE 90675"
    },
    "tax": {
        "base_ht": 459.16,
        "regulations": 18.93,
        "total_ht": 380.88,
        "vat_amount": 96.32,
        "vat_percentage": 25.57
    }
}