{
    "buyer": {
        "address": "641 Gary Parkway West Susan, WV 18346",
        "business_no": "rk014",
        "id": "hg592"
    },
    "invoice": {
        "date": "29.01.2019",
        "number": "1505-3007"
    },
    "payment": {
        "due_date": "19.03.2009",
        "total": 307.09
    },
    "products": [
        {
            "amount": 234.16,
            "description": "syndicate compelling web services",
            "quantity": 8.55,
            "reference": "Vr-509",
            "unit_price": 18.63
        },
        {
            "amount": 134.18,
            "description": "iterate customized bandwidth",
            "quantity": 1.45,
            "reference": "ZI-734",
            "unit_price": 92.71
        },
        {
            "amount": 173.77,
            "description": "grow intuitive e-services",
            "quantity": 2.88,
            "reference": "NE-293",
            "unit_price": 45.43
        },
        {
            "amount": 75.94,
            "description": "engage scalable methodologies",
            "quantity": 2.31,
            "reference": "Mk-351",
            "unit_price": 13.75
        },
        {
            "amount": 372.9,
            "description": "reinvent cross-platform experiences",
            "quantity": 4.48,
            "reference": "El-498",
            "unit_price": 96.95
        },
        {
            "amount": 242.22,
            "description": "morph bleeding-edge platforms",
            "quantity": 8.08,
            "reference": "tO-809",
            "unit_price": 68.16
        },
        {
            "amount": 84.15,
            "description": "drive B2C e-business",
            "quantity": 5.78,
            "reference": "RZ-128",
            "unit_price": 55.34
        }
    ],
    "seller": {
        "address": "4609 Brian Streets Suite 442 Chapmanton, OK 54019"
    },
    "tax": {
        "base_ht": 345.99,
        "regulations": 10.53,
        "total_ht": 434.52,
        "vat_amount": 30.71,
        "vat_percentage": 26.65
    }
}