{
    "buyer": {
        "address": "PSC 0894, Box 7561 APO AE 36693",
        "company_name": "Kennedy, White and Herrera",
        "country": "Tajikistan",
        "name": "Lynn Spears MD"
    },
    "invoice": {
        "date": "30.10.2023",
        "number": 555148
    },
    "payment": {
        "discount_amount": 47.94,
        "discount_percentage": 5.36,
        "due": 133.7,
        "sub_total": 156.93,
        "total": 627.28
    },
    "products": [
        {
            "description": "scale integrated methodologies",
            "index": "8",
            "quantity": 5.26,
            "total_price": 98.16,
            "unit_price": 31.72
        },
        {
            "description": "empower dot-com vortals",
            "index": "2",
            "quantity": 8.41,
            "total_price": 450.07,
            "unit_price": 42.3
        },
        {
            "description": "grow turn-key web-readiness",
            "index": "6",
            "quantity": 3.09,
            "total_price": 260.34,
            "unit_price": 81.19
        }
    ],
    "seller": {
        "address": "408 Elizabeth Village Port Kayla, CA 33412",
        "company_name": "Allen-Jones",
        "vat_no": "oK73957459262"
    }
}